workflow_keeper/__init__.py
workflow_keeper/__main__.py
workflow_keeper/actions.py
workflow_keeper/components.py
workflow_keeper/config.py
workflow_keeper/controller.py
workflow_keeper/datamodels.py
workflow_keeper/server.py
workflow_keeper/utils.py
workflow_keeper-0.0.3.dist-info/METADATA
workflow_keeper-0.0.3.dist-info/WHEEL
workflow_keeper-0.0.3.dist-info/top_level.txt
workflow_keeper-0.0.3.dist-info/RECORD
