Metadata-Version: 2.1
Name: workflow-keeper
Version: 0.0.3
Summary: Driver for Arizona USB Pressure Sensor
Author: davidliyutong
Author-email: davidliyutong@sjtu.edu.cn
Requires-Python: >=3.7
Requires-Dist: vyper-config >=1.1.1
Requires-Dist: loguru >=0.7.0
Requires-Dist: click >=8.1.3
Requires-Dist: pika >=1.3.2
Requires-Dist: fastapi >=0.97.0
Requires-Dist: uvicorn >=0.22.0
Requires-Dist: requests >=2.31.0
Requires-Dist: openapi-python-client >=0.14.1
Requires-Dist: websockets >=11.0.3
Requires-Dist: paramiko >=3.3.1
Requires-Dist: croniter >=1.4.1
Requires-Dist: watchdog >=3.0.0
Requires-Dist: apscheduler >=3.10.4
